setup.py
observa/__init__.py
observa/config.py
observa/event.py
observa/observer.py
observa/server.py
observa/test.py
observa/test2.py
observa/util.py
observa/zero_code.py
observa.egg-info/PKG-INFO
observa.egg-info/SOURCES.txt
observa.egg-info/dependency_links.txt
observa.egg-info/requires.txt
observa.egg-info/top_level.txt