Metadata-Version: 2.1
Name: observa
Version: 1.1.2
Summary: observa API
Home-page: https://github.com
Author: chendong
Author-email: chendong@google.com
License: MIT
Keywords: API,AI,Python
Platform: UNKNOWN
Requires-Python: >=3.9
